dicom_utils/__init__.py
dicom_utils/__main__.py
dicom_utils/_tag_enum.py
dicom_utils/anonymize.py
dicom_utils/basic_offset_table.py
dicom_utils/cli/__init__.py
dicom_utils/cli/cat.py
dicom_utils/cli/decompress.py
dicom_utils/cli/dicom2img.py
dicom_utils/cli/dicom_types.py
dicom_utils/cli/dicomphi.py
dicom_utils/cli/find.py
dicom_utils/cli/hash.py
dicom_utils/cli/merge_series.py
dicom_utils/cli/organize.py
dicom_utils/cli/overlap.py
dicom_utils/cli/project.py
dicom_utils/cli/strip.py
dicom_utils/cli/validate.py
dicom_utils/container/__init__.py
dicom_utils/container/collection.py
dicom_utils/container/group.py
dicom_utils/container/helpers.py
dicom_utils/container/input.py
dicom_utils/container/output.py
dicom_utils/container/protocols.py
dicom_utils/container/record.py
dicom_utils/dicom.py
dicom_utils/dicom_factory.py
dicom_utils/find_phi.py
dicom_utils/logging.py
dicom_utils/merge_series.py
dicom_utils/metadata.py
dicom_utils/private.py
dicom_utils/tags.py
dicom_utils/types.py
dicom_utils/validation.py
dicom_utils/version.py
dicom_utils/visualize.py
dicom_utils/volume.py
dicom_utils-1.0.11.dist-info/entry_points.txt
dicom_utils-1.0.11.dist-info/WHEEL
dicom_utils-1.0.11.dist-info/METADATA
dicom_utils-1.0.11.dist-info/licenses/LICENSE
dicom_utils-1.0.11.dist-info/RECORD
