Metadata-Version: 2.1
Name: dicom-utils
Version: 1.0.11
Summary: Utility functions for easy DICOM management.
License: Apache
Author-email: Scott Chase Waggener <tidalpaladin@protonmail.com>,Tim Cogan <tim@medcognetics.com>
Requires-Python: >=3.10,<3.13
Requires-Dist: Pillow
Requires-Dist: callable-registry
Requires-Dist: colorama
Requires-Dist: dicom-anon==1.0.13post2
Requires-Dist: matplotlib
Requires-Dist: numpy
Requires-Dist: opencv-python
Requires-Dist: pydicom>=3
Requires-Dist: pylibjpeg
Requires-Dist: pylibjpeg-openjpeg
Requires-Dist: python-gdcm>=3.0.10
Requires-Dist: tqdm-multiprocessing
Provides-Extra: j2k
Requires-Dist: pynvjpeg2k; extra == "j2k"
